[{"rating": 5.0, "review": "Quick delivery, great product", "verified": false, "helpfulness": "0/0", "author": "Dereement"}, {"rating": 4.0, "review": "Apple TV is a lot of fun.  Small and easy to move around the house to different TV's.", "verified": true, "helpfulness": "0/0", "author": "The Chapps"}, {"rating": 4.0, "review": "Great unit.  Use it everyday.  Wish it had the ability to download a movie for use later while off line.", "verified": false, "helpfulness": "0/0", "author": "Schmidty \"mankatoallen3147\""}, {"rating": 5.0, "review": "Fantastic", "verified": true, "helpfulness": "1/1", "author": "scottiep"}, {"rating": 5.0, "review": "Pretty cool - I love all the apps and airplay.", "verified": true, "helpfulness": "0/0", "author": "Victoriag87"}, {"rating": 5.0, "review": "Love its mirror and airplay function. It brings me so much joy when I do random slide show of my Flickr albums with iTune music for background on my large screen TV and Hi-Fi speaker system!", "verified": true, "helpfulness": "0/0", "author": "Simon Zhang"}, {"rating": 5.0, "review": "Love my Apple TV now that I have one that works ... My first one came and didn't work... Love it", "verified": true, "helpfulness": "0/0", "author": "Toodie"}, {"rating": 5.0, "review": "Super friendly", "verified": true, "helpfulness": "0/0", "author": "Alex"}, {"rating": 5.0, "review": "I just wished I had waited a little while as Apple just announced a 30% price drop on the Apple TV.", "verified": true, "helpfulness": "2/2", "author": "Robert C. Yates"}, {"rating": 5.0, "review": "Very pleased with the order, it's timing and the product.", "verified": true, "helpfulness": "0/0", "author": "Michael L. Pettegrew"}]