[{"rating": 5.0, "review": "Awesome", "verified": true, "helpfulness": "0/0", "author": "Michael Hultgren"}, {"rating": 4.0, "review": "The unit does everything that they say it does and is working very well.I don\u2019t really care for the voice activated control the manual remote control is easier to use.They should add more directions about the cables you will need to purchase to set the system up on the product description so you will know what to purchase.However, I am happy with the unit and will probably purchase the fire stick to use when I\u2019m traveling.", "verified": true, "helpfulness": "0/0", "author": "CrabbyAbby"}, {"rating": 4.0, "review": "Sometimes the connection is slow but I like the access to streaming movies.", "verified": true, "helpfulness": "0/0", "author": "Happy in life"}, {"rating": 5.0, "review": "Fast and easy to set up, love the selection of movies and TV shows. I am now spoiled!", "verified": true, "helpfulness": "0/0", "author": "Jim Barstow"}, {"rating": 5.0, "review": "More than what I expected", "verified": true, "helpfulness": "0/0", "author": "christopher smith"}, {"rating": 5.0, "review": "Works great.  No problems and  easy to use.", "verified": true, "helpfulness": "0/0", "author": "Amazon Customer"}, {"rating": 5.0, "review": "Simple to setup, good wifi reception", "verified": true, "helpfulness": "0/0", "author": "Mark"}, {"rating": 5.0, "review": "Works great!", "verified": true, "helpfulness": "0/0", "author": "Amanda"}, {"rating": 4.0, "review": "Amazon is great using the fire TV.  Netflix, not any better than using ROKU.", "verified": true, "helpfulness": "0/0", "author": "Kenneth"}, {"rating": 5.0, "review": "Works great, saved $20 on refurbished. Simple to hookup and use.", "verified": true, "helpfulness": "0/0", "author": "Ronald C Warnke"}]