[{"rating": 5.0, "review": "Nice", "verified": false, "helpfulness": "0/0", "author": "salvador"}, {"rating": 4.0, "review": "Nice", "verified": true, "helpfulness": "0/0", "author": "Jerome Overstreet Jr"}, {"rating": 3.0, "review": "Roku is better. The Fire TV Stick has to be in line of sight to the router and I can't load Netflix. Wish I would have bought another Roku.", "verified": true, "helpfulness": "0/0", "author": "Maxwell"}, {"rating": 5.0, "review": "This gadget is awesome and easy to use.  Highly  recommended.", "verified": true, "helpfulness": "0/0", "author": "Mario Cordova"}, {"rating": 5.0, "review": "Awesome", "verified": true, "helpfulness": "0/0", "author": "Hk"}, {"rating": 4.0, "review": "It was easy to set up and really easy to use", "verified": true, "helpfulness": "0/0", "author": "Catrina \"Catrina\""}, {"rating": 3.0, "review": "Works well.  Wish I could remove icons I don't use.", "verified": true, "helpfulness": "0/0", "author": "Mike Weaver"}, {"rating": 5.0, "review": "So easy to set up and use!  Goodbye forever, cable tv!", "verified": true, "helpfulness": "0/0", "author": "Katherine Parton"}, {"rating": 5.0, "review": "Great product. Sirve en CR", "verified": true, "helpfulness": "0/0", "author": "Amazon Customer"}, {"rating": 5.0, "review": "It works", "verified": true, "helpfulness": "0/0", "author": "Misti Svoboda"}]