[{"rating": 5.0, "review": "Awesome product..thanks amazon", "verified": true, "helpfulness": "0/0", "author": "Sudheer"}, {"rating": 5.0, "review": "Excellent, it works perfect and I got the item on time.", "verified": true, "helpfulness": "0/0", "author": "Karim Vivanco"}, {"rating": 5.0, "review": "So far I have zero complaints with the Chromecast.  I love being able to control it from my computer, phone or iPad.  I also like that it doesn't have it's own interface and menus I have to fight through (i.e. Roku).  I have a much easier time finding what I want to watch on my phone and then \"casting\" it to the TV.", "verified": true, "helpfulness": "0/0", "author": "Warren G"}, {"rating": 5.0, "review": "Excellent", "verified": true, "helpfulness": "0/0", "author": "Anand"}, {"rating": 5.0, "review": "Very cool. I can easily connect from any device running a windows tabs such as 8.1 or win10..and from inside google browser...but really cool is the many functions from my Android smart phone direct to the tv.", "verified": true, "helpfulness": "0/0", "author": "K. Bell \"Gramps\""}, {"rating": 4.0, "review": "Sometimes photos preview is blurred, but globally it's OK.", "verified": true, "helpfulness": "0/0", "author": "Dario Mastilovic"}, {"rating": 5.0, "review": "Great now that I can mirror my device's screen!", "verified": true, "helpfulness": "0/0", "author": "Elena"}, {"rating": 5.0, "review": "Love it", "verified": true, "helpfulness": "0/0", "author": "Jesus Medina"}, {"rating": 2.0, "review": "TV display often gets out of sync with phone app making it difficult to control play, stop, rewind, ...", "verified": true, "helpfulness": "0/0", "author": "James Bokros"}, {"rating": 5.0, "review": "Works great.  Amazing price.", "verified": true, "helpfulness": "0/0", "author": "J. Gregory"}]