[{"rating": 5.0, "review": "Great!", "verified": true, "helpfulness": "0/0", "author": "Michael Oyler"}, {"rating": 4.0, "review": "When more apps come out tied into this tech it will definitely be worth it. But for now, go with the roku 3.", "verified": true, "helpfulness": "0/0", "author": "g"}, {"rating": 1.0, "review": "It's so hard to get this to work. We have given up on it. It only works on a limited websites.", "verified": true, "helpfulness": "0/0", "author": "goldenbrown"}, {"rating": 5.0, "review": "Very easy to set up and use. I have a couple of these in my house. Love them. Would highly recommend.", "verified": true, "helpfulness": "0/0", "author": "J. Penn"}, {"rating": 1.0, "review": "Good idea...possible that I do not know all the benefits...I found set up and operation clunky...now in disuse after I went out again and bought an Apple TV...agree I paid more but I have ease of use and peace of mind...", "verified": true, "helpfulness": "0/0", "author": "BM"}, {"rating": 3.0, "review": "Would love to be able to stream all my apps(MTV,vh1,etc) but overall a great product!!", "verified": true, "helpfulness": "0/0", "author": "Karry Wiggins"}, {"rating": 1.0, "review": "Don't work with dlink", "verified": true, "helpfulness": "0/0", "author": "guy greenberg"}, {"rating": 5.0, "review": "I love this thing! Works great with all of our devices, android, Iphones, windows.", "verified": true, "helpfulness": "0/0", "author": "Amazon Customer"}, {"rating": 5.0, "review": "Super", "verified": true, "helpfulness": "0/0", "author": "Sychov Alexander"}, {"rating": 5.0, "review": "Awesome", "verified": true, "helpfulness": "0/0", "author": "Kenneth M. Becker"}]