[{"rating": 1.0, "review": "This is among the worst products I've ever purchased. It rarely works. It constantly jumps off the network. Basically every time I want to use it, I have to go through a 20 minute troubleshooting process:Restart the chromecastReset my wirelessReset up the chromecastOh what's that? Still not working?!!*starts over*Next morning I wake up and have to do it all over again.It sucks. I wish I could send it in a gift wrapped box back to the engineers and product managers who manage the product. It shouldn't be this difficult. It should just work.", "verified": true, "helpfulness": "0/0", "author": "Boz1200"}, {"rating": 3.0, "review": "ok,ok", "verified": true, "helpfulness": "0/0", "author": "wayne w jackson"}, {"rating": 5.0, "review": "Fantastic!", "verified": true, "helpfulness": "0/1", "author": "Nickolas Geeker \"Nickolas Geeker\""}, {"rating": 1.0, "review": "piece of junk not worth 40 bucks I got it as a gift and got rid of it don't waste your money", "verified": true, "helpfulness": "0/0", "author": "Larry Sprissler"}, {"rating": 5.0, "review": "what everyone needs to make their tvs smart for less, and no surveillance for ad purposes built in.", "verified": true, "helpfulness": "0/0", "author": "Christopher Parsons"}, {"rating": 5.0, "review": "Cool", "verified": true, "helpfulness": "0/0", "author": "Viet Mai"}, {"rating": 3.0, "review": "May work for others but didnt work well for me.  Returned", "verified": true, "helpfulness": "0/0", "author": "Ryan H"}, {"rating": 3.0, "review": "works well", "verified": true, "helpfulness": "0/0", "author": "D John"}, {"rating": 5.0, "review": "It is nice ..I like it", "verified": true, "helpfulness": "0/0", "author": "Teshome"}, {"rating": 3.0, "review": "ya, its pretty good device,", "verified": true, "helpfulness": "0/0", "author": "Soumendra Karmahapatra"}]