[{"rating": 4.0, "review": "It's really cool but if you unplug it from the power source it will mess it up and you'll have to re-setup the thing.", "verified": true, "helpfulness": "0/0", "author": "Michael Brann"}, {"rating": 4.0, "review": "i gave it to a friend as a gift.", "verified": true, "helpfulness": "0/0", "author": "sabah malak"}, {"rating": 5.0, "review": "Can say enough about it ,,,works great ...RIP cable bill!", "verified": true, "helpfulness": "0/0", "author": "Danny Springs"}, {"rating": 5.0, "review": "Good price, works as advertised with both iPad and iPhone apps. Wish it worked with Amazon video, but it does not. I own an Apple TV (also no Amazon video capability). Therefore my option is to buy video content from Google or Apple or another device (Fire TV) from Amazon. Don't think I'll be doing that anytime soon. Make sure you understand what you can and can't access via these devices before you purchase any of them.", "verified": true, "helpfulness": "0/0", "author": "Geoffrey"}, {"rating": 5.0, "review": "Have one on every TV/  Can broadcast from phone IPAD and computer right to TV plus so much more!", "verified": true, "helpfulness": "0/0", "author": "mudstock"}, {"rating": 5.0, "review": "Love it !", "verified": true, "helpfulness": "0/0", "author": "Marce"}, {"rating": 5.0, "review": "Excellent", "verified": true, "helpfulness": "0/0", "author": "Ahmad"}, {"rating": 5.0, "review": "Excellent", "verified": true, "helpfulness": "0/0", "author": "Louis   Williams"}, {"rating": 4.0, "review": "Got it together with Slingbox M1, but Slingplayer app not working yet, otherwise everything ok.", "verified": true, "helpfulness": "0/0", "author": "Marc C Gabriel"}, {"rating": 5.0, "review": "excellent very fast", "verified": true, "helpfulness": "0/0", "author": "Johan P."}]