[{"rating": 5.0, "review": "Easy to setup and use!", "verified": true, "helpfulness": "0/0", "author": "C. Harris"}, {"rating": 5.0, "review": "Works great and was effortless to install. I was watching Netflix within minutes of plugging it in first time!  Now it is always ready,even if I plug it I to a different TV!! Love it!!", "verified": true, "helpfulness": "0/0", "author": "jeanne a smith"}, {"rating": 5.0, "review": "The Fire TV Stick is easy to install and easy to use.  It's helpful to be an Amazon Prime member since this allows you to access tons of movies and TV shows.  The picture quality is great.  The Fire Stick is a good value.", "verified": true, "helpfulness": "0/0", "author": "M"}, {"rating": 5.0, "review": "Very useful", "verified": true, "helpfulness": "0/0", "author": "Rudy Gracia"}, {"rating": 5.0, "review": "Easy, inexpensive, great product and service.", "verified": true, "helpfulness": "0/0", "author": "Jason W Branch"}, {"rating": 5.0, "review": "Works like it says it does. Its a good price for a good product.", "verified": true, "helpfulness": "0/0", "author": "Heather Semore"}, {"rating": 4.0, "review": "Very simple yet elegant to use.", "verified": true, "helpfulness": "0/0", "author": "Jody Kulchinsky"}, {"rating": 5.0, "review": "Got this for my father for Father's Day! He loves it. Plus it was very easy to set-up!", "verified": true, "helpfulness": "0/0", "author": "KT"}, {"rating": 5.0, "review": "Only downside I never want to leave my couch", "verified": true, "helpfulness": "0/0", "author": "Beth"}, {"rating": 5.0, "review": "The fire stick is perfect! It has everything I need.", "verified": true, "helpfulness": "0/0", "author": "gina marie vodola"}]