[{"rating": 5.0, "review": "great way to help cut the cord", "verified": true, "helpfulness": "0/0", "author": "robert bruce"}, {"rating": 5.0, "review": "Good", "verified": true, "helpfulness": "0/0", "author": "jose ivan ruiz gonzalez"}, {"rating": 4.0, "review": "Intuitive to use. Easy install.", "verified": true, "helpfulness": "0/0", "author": "Ben D"}, {"rating": 5.0, "review": "Great item, easy to set up and use.", "verified": true, "helpfulness": "0/0", "author": "JS"}, {"rating": 5.0, "review": "Nice and simple to use.", "verified": true, "helpfulness": "0/0", "author": "Dogwhisper"}, {"rating": 5.0, "review": "Awesome!", "verified": true, "helpfulness": "0/0", "author": "Juan Jose Peralta"}, {"rating": 5.0, "review": "Had Chromecast before this, and now I am fully converted to Fire TV Stick. Great product!", "verified": true, "helpfulness": "0/0", "author": "Joe"}, {"rating": 5.0, "review": "Excellent product so far. Much more pleased with it than chrome cast", "verified": true, "helpfulness": "0/0", "author": "123"}, {"rating": 5.0, "review": "Fire stick >>>>>>> Apple tv", "verified": true, "helpfulness": "0/0", "author": "Israel Mcbride"}, {"rating": 5.0, "review": "Loving it!", "verified": true, "helpfulness": "0/0", "author": "andy"}]