[{"rating": 5.0, "review": "Bought as an alternative to cable. Loving it so far.", "verified": true, "helpfulness": "0/0", "author": "nicole"}, {"rating": 5.0, "review": "This fire tv stick has met my expectations more than I could have imagined.  I am renting a home with a tv but does not have netflix, or hulu or prime and I ordered Amazon fire tv stick and now I am hooked up 24/7 to the tv I like when I want to watch it. And an added bonus I get music as well.  I highly recommend this to anyone with internet capabilities to watch whatever, whenever and where ever you wish.  And the price is excellent.", "verified": true, "helpfulness": "0/0", "author": "amazonshopper1"}, {"rating": 5.0, "review": "I am so pleased at what one can do with the \"stick\" -- movies, TV, photos, music. What a find!", "verified": true, "helpfulness": "0/0", "author": "Nancy Galster"}, {"rating": 5.0, "review": "Works great no more movie rentals", "verified": true, "helpfulness": "0/0", "author": "Kimberly Hart"}, {"rating": 4.0, "review": "Works fine, we are pleased.", "verified": true, "helpfulness": "0/0", "author": "Bob Rowntree"}, {"rating": 1.0, "review": "Amazon banned Kodi media center app for invalid reasons.", "verified": true, "helpfulness": "0/0", "author": "JuanBoro"}, {"rating": 4.0, "review": "I'm truly enjoying my Fire Stick!", "verified": true, "helpfulness": "0/0", "author": "Amazon Customer"}, {"rating": 5.0, "review": "Love it!  Having so much fun seeing new shows and lots of movies.", "verified": true, "helpfulness": "0/0", "author": "Sher \"Book Lover\""}, {"rating": 5.0, "review": "Perfect!", "verified": true, "helpfulness": "0/0", "author": "Carlos Antonetti"}, {"rating": 5.0, "review": "Love this little thing!!!", "verified": true, "helpfulness": "0/0", "author": "Melissa Marie Glass \"Riley's Mommy\""}]