[{"rating": 2.0, "review": "Can't enjoy movies because it is constantly trying to spool up the movie.  Very aggravating.", "verified": true, "helpfulness": "0/0", "author": "Janice \"Janice\""}, {"rating": 5.0, "review": "This little guy opens the door to so many shows and movies to watch! So simple to set up and use. I highly recommend it to anyone sick of the same ol' on tv.", "verified": true, "helpfulness": "0/0", "author": "Susana Fonticoba"}, {"rating": 5.0, "review": "Very Powerful with addons and great HD display.", "verified": true, "helpfulness": "0/0", "author": "Sinny24"}, {"rating": 5.0, "review": "I do enjoy having the fire stick.  For me taking in shows that have not seen before cause they were on premium channels.  Would recommend it to those who want to cut back on cable bills.", "verified": true, "helpfulness": "1/1", "author": "John"}, {"rating": 5.0, "review": "Must. Put. Down. Remote.......It's everything I hoped it would be!", "verified": true, "helpfulness": "0/0", "author": "Justin Lafollette"}, {"rating": 5.0, "review": "Works as stated love it", "verified": true, "helpfulness": "0/0", "author": "Stacey Harlan"}, {"rating": 4.0, "review": "Provides great streaming of apps to a TV that does not have smart capabilities. Easy to use. Great price.", "verified": true, "helpfulness": "0/0", "author": "Robert"}, {"rating": 4.0, "review": "Easy to set up and use.", "verified": true, "helpfulness": "0/0", "author": "S. Brewer"}, {"rating": 4.0, "review": "quick to set up and get going. many apps require account activation via computer which is a bit annoying.", "verified": true, "helpfulness": "0/1", "author": "kcwizfan"}, {"rating": 5.0, "review": "I am absolutely happy that the fire stick allows me to catch up on episodes missed !", "verified": true, "helpfulness": "0/0", "author": "Johnell Todaro"}]