[{"rating": 1.0, "review": "I sent it back, too much work.  My grandsons are moving so there goes my tech support team!!", "verified": true, "helpfulness": "0/2", "author": "leenie"}, {"rating": 5.0, "review": "Love it!!!", "verified": true, "helpfulness": "0/1", "author": "Yvette mc caleb"}, {"rating": 5.0, "review": "Works great and was easy to set up!", "verified": true, "helpfulness": "0/1", "author": "David"}, {"rating": 5.0, "review": "Love it. No complaints!", "verified": true, "helpfulness": "0/1", "author": "Endya"}, {"rating": 5.0, "review": "Great deal, The instructions could be better on how to install and operate the hand held", "verified": true, "helpfulness": "0/1", "author": "William Lea"}, {"rating": 3.0, "review": "I'm a little old school.  The menus could be easier to navigate with the remote.  A specific search function would be great for titles andante adding the qwerty keyboard to the app remote on my phone.", "verified": true, "helpfulness": "0/1", "author": "Fred White"}, {"rating": 5.0, "review": "I did have to use the extender so it would pick-up the wifi signal better and after that it has been a dream.Hooked it up in my son's room so he can watch what he wants without paying a fortune for an extra cable box.I also use it to catch up on past seasons of some of the shows I watch.Going to check out the games portion sometime soon.", "verified": true, "helpfulness": "0/1", "author": "Lisa M Heckel"}, {"rating": 5.0, "review": "Love it", "verified": true, "helpfulness": "0/1", "author": "Brittany way"}, {"rating": 4.0, "review": "Very easy to use", "verified": true, "helpfulness": "0/1", "author": "kevin revelette"}, {"rating": 5.0, "review": "Great", "verified": true, "helpfulness": "0/1", "author": "Marat Mitelman"}]