[{"rating": 4.0, "review": "it was a nice try.it did not have its listed amount of memory.has the same as the firetv box.it is easy to upload kodi and other programs to it.not all will run right.they do put out a beautiful picture.the screen savers are the best to watch.fantastic portraits.both units have amazon looking over your back.it would be nice to just have the unit to yourself.but you are constantly tracked.both units are now back in their boxes.kodi has to many limits on them.i have a unit coming from china with 32gb of memory in it.it is a dual computer.windows 8 and android 4.4.it should be something.intel cpu.small but powerful.", "verified": true, "helpfulness": "0/0", "author": "ray"}, {"rating": 5.0, "review": "I love it, love it, love it..... Did I mention that I love it.", "verified": true, "helpfulness": "0/0", "author": "J. Getty \"Mermaid\""}, {"rating": 5.0, "review": "works great", "verified": true, "helpfulness": "0/0", "author": "Diana LaComfora"}, {"rating": 5.0, "review": "tOO MUCH TO LIST. i LOVE IT.", "verified": true, "helpfulness": "0/0", "author": "Amazon Customer"}, {"rating": 5.0, "review": "works great, fast, and love the free games and other apps you can download.", "verified": true, "helpfulness": "0/0", "author": "The Daver"}, {"rating": 1.0, "review": "Very slow downloading anything (tried both YouTube and Netflix). Don't have that issue with Netflix on the Wii. So staying with Netflix on the Wii instead.", "verified": true, "helpfulness": "0/0", "author": "Henk G Neefs"}, {"rating": 1.0, "review": "If I had it to do over again I wouldn't buy it. Did not meet expectations.", "verified": true, "helpfulness": "0/0", "author": "robin Axtell"}, {"rating": 5.0, "review": "Very good", "verified": true, "helpfulness": "0/0", "author": "Roberto moraga"}, {"rating": 4.0, "review": "Streaming good. Would be nice to have early released movies with no additional fees", "verified": true, "helpfulness": "0/0", "author": "Brian"}, {"rating": 5.0, "review": "A+ all the way!!!!", "verified": true, "helpfulness": "0/0", "author": "Amazon Fan"}]